data_intelligence/__init__.py
data_intelligence/historical_analysis/plot_config.py
data_intelligence/historical_analysis/dashboard/general_dashboard.py
data_intelligence/historical_analysis/dashboard/time_analysis.py
data_intelligence/historical_analysis/dashboard/utils.py
data_intelligence/historical_analysis/data_processing/aggregation.py
data_intelligence/historical_analysis/data_processing/anomalies.py
data_intelligence/historical_analysis/data_processing/patterns.py
data_intelligence/infraction_index_engine/engine.py
data_intelligence/infraction_index_engine/ml_solutions/system_analyzer/evaluate.py
data_intelligence/infraction_index_engine/ml_solutions/system_analyzer/features.py
data_intelligence/infraction_index_engine/ml_solutions/system_analyzer/model.py
data_intelligence/infraction_index_engine/ml_solutions/system_analyzer/preprocess.py
data_intelligence/infraction_index_engine/ml_solutions/system_analyzer/query.py
data_intelligence/infraction_index_engine/ml_solutions/system_analyzer/train.py
data_intelligence/infraction_index_engine/ml_solutions/system_analyzer/user_model.py
data_intelligence/infraction_index_engine/ml_solutions/visual_telemetry/cloudflare.py
data_intelligence/infraction_index_engine/ml_solutions/visual_telemetry/convert.py
data_intelligence/infraction_index_engine/ml_solutions/visual_telemetry/model/gemini.py
data_intelligence/infraction_index_engine/productivity_forecast/data/loader.py
data_intelligence/infraction_index_engine/productivity_forecast/data/preprocess.py
data_intelligence/infraction_index_engine/productivity_forecast/model/predictor.py
data_intelligence/models/Process.py
data_intelligence/models/Worker.py
data_intelligence/models/database.py
data_intelligence/models/object_storage.py
monitoria_data_intelligence-1.0.1.dist-info/licenses/LICENSE
monitoria_data_intelligence-1.0.1.dist-info/METADATA
monitoria_data_intelligence-1.0.1.dist-info/WHEEL
monitoria_data_intelligence-1.0.1.dist-info/top_level.txt
monitoria_data_intelligence-1.0.1.dist-info/RECORD
