Metadata-Version: 2.4
Name: monitoria_data_intelligence
Version: 1.0.1
Summary: Centralizes the MonitorIA data and intelligence layer, including visual telemetry AI, real-time process monitoring, predictive and historical analysis, score integration, and productivity metrics, exposed as an SDK for backend consumption, supporting automated decisions, dashboards, and alerts.
Author-email: Eduardo Costa Amex Macal <eduardocosta942z@gmail.com>, Lorenzo Lima de Oliveira <lorenzolimadeoliveira2010@gmail.com>, Carlos Eduardo Domingues Bellomo  <cadu@bellomo.blog.br>
License: MIT License
License-File: LICENSE
Dynamic: license-file
